s3watcher/__init__.py
s3watcher/client.py
s3watcher/exceptions.py
s3watcher/log.py
s3watcher/message.py
s3watcher/server.py
s3watcher-0.1.0.dist-info/LICENSE.txt
s3watcher-0.1.0.dist-info/METADATA
s3watcher-0.1.0.dist-info/WHEEL
s3watcher-0.1.0.dist-info/top_level.txt
s3watcher-0.1.0.dist-info/RECORD
