Metadata-Version: 2.1
Name: s3watcher
Version: 0.1.0
Summary: Watch AWS S3 bucket contents
Home-page: https://github.com/dbnicholson/s3watcher
Author: Dan Nicholson
Author-email: nicholson@endlessm.com
License: UNKNOWN
Platform: UNKNOWN
Classifier: Programming Language :: Python :: 3
Classifier: License :: OSI Approved :: GNU General Public License v2 or later (GPLv2+)
Classifier: Operating System :: POSIX
Requires-Python: >=3.7
Requires-Dist: boto3
Requires-Dist: msgpack
